jumpthegun.sh
jumpthegun/__init__.py
jumpthegun/__version__.py
jumpthegun/config.py
jumpthegun/env_vars.py
jumpthegun/io_redirect.py
jumpthegun/jumpthegunctl.py
jumpthegun/runtime_dir.py
jumpthegun/tools.py
jumpthegun/utils.py
jumpthegun/_vendor/__init__.py
jumpthegun/_vendor/filelock/LICENSE
jumpthegun/_vendor/filelock/README.md
jumpthegun/_vendor/filelock/VERSION
jumpthegun/_vendor/filelock/__init__.py
jumpthegun/_vendor/filelock/_api.py
jumpthegun/_vendor/filelock/_error.py
jumpthegun/_vendor/filelock/_soft.py
jumpthegun/_vendor/filelock/_unix.py
jumpthegun/_vendor/filelock/_util.py
jumpthegun/_vendor/filelock/_windows.py
jumpthegun/_vendor/filelock/py.typed
jumpthegun/_vendor/filelock/version.py
jumpthegun-0.2.0.data/data/bin/jumpthegun
jumpthegun-0.2.0.dist-info/METADATA
jumpthegun-0.2.0.dist-info/WHEEL
jumpthegun-0.2.0.dist-info/entry_points.txt
jumpthegun-0.2.0.dist-info/licenses/LICENSE
jumpthegun-0.2.0.dist-info/RECORD
