Metadata-Version: 2.4
Name: jumpthegun
Version: 0.2.0
Summary: Make Python CLI tools win the speed race, by cheating!
Project-URL: Homepage, https://github.com/taleinat/jumpthegun
Author-email: Tal Einat <taleinat@gmail.com>
License: Apache-2.0
License-File: LICENSE
Keywords: cli
Classifier: Development Status :: 1 - Planning
Classifier: Environment :: Console
Classifier: Intended Audience :: Developers
Classifier: License :: OSI Approved :: Apache Software License
Classifier: Operating System :: MacOS :: MacOS X
Classifier: Operating System :: POSIX :: Linux
Classifier: Programming Language :: Python
Classifier: Programming Language :: Python :: 3 :: Only
Classifier: Programming Language :: Python :: 3.8
Classifier: Programming Language :: Python :: 3.9
Classifier: Programming Language :: Python :: 3.10
Classifier: Programming Language :: Python :: 3.11
Classifier: Programming Language :: Python :: 3.12
Classifier: Programming Language :: Python :: 3.13
Classifier: Programming Language :: Python :: 3.14
Classifier: Topic :: Software Development :: Libraries
Requires-Python: >=3.8
Provides-Extra: test
Requires-Dist: pytest<8,>=7; extra == 'test'
